mlalib/__init__.py
mlalib/tabular/datasets/__init__.py
mlalib/tabular/datasets/_titanic.py
mlalib/tabular/datasets/_uci_datasets.py
mlalib/tabular/transforms/__init__.py
mlalib/tabular/transforms/_base_colwise_transform.py
mlalib/tabular/transforms/_transforms.py
mlalib/tabular/utils/__init__.py
mlalib/tabular/utils/data/__init__.py
mlalib/tabular/utils/data/_dataloaders.py
mlalib/tabular/utils/data/_uci_utils.py
mlalib/utils/__init__.py
mlalib/utils/_base_nn_trainer.py
mlalib/utils/_utils.py
mlalib-0.5.1.dist-info/licenses/LICENSE
mlalib-0.5.1.dist-info/METADATA
mlalib-0.5.1.dist-info/WHEEL
mlalib-0.5.1.dist-info/top_level.txt
mlalib-0.5.1.dist-info/RECORD
